py_avataaars/__init__.py
py_avataaars/templates/base.svg
py_avataaars/templates/face.svg
py_avataaars/templates/main.svg
py_avataaars/templates/skin.svg
py_avataaars/templates/clothes/blazer_shirt.svg
py_avataaars/templates/clothes/blazer_sweater.svg
py_avataaars/templates/clothes/clothe_color.svg
py_avataaars/templates/clothes/collar_sweater.svg
py_avataaars/templates/clothes/graphic_shirt.svg
py_avataaars/templates/clothes/hoodie.svg
py_avataaars/templates/clothes/overall.svg
py_avataaars/templates/clothes/shirt_crew_neck.svg
py_avataaars/templates/clothes/shirt_scoop_neck.svg
py_avataaars/templates/clothes/shirt_v_neck.svg
py_avataaars/templates/clothes/graphics/bat.svg
py_avataaars/templates/clothes/graphics/bear.svg
py_avataaars/templates/clothes/graphics/cumbia.svg
py_avataaars/templates/clothes/graphics/deer.svg
py_avataaars/templates/clothes/graphics/diamond.svg
py_avataaars/templates/clothes/graphics/hola.svg
py_avataaars/templates/clothes/graphics/pizza.svg
py_avataaars/templates/clothes/graphics/resist.svg
py_avataaars/templates/clothes/graphics/selena.svg
py_avataaars/templates/clothes/graphics/skull.svg
py_avataaars/templates/clothes/graphics/skull_outline.svg
py_avataaars/templates/face/eyebrow/angry.svg
py_avataaars/templates/face/eyebrow/angry_natural.svg
py_avataaars/templates/face/eyebrow/default.svg
py_avataaars/templates/face/eyebrow/default_natural.svg
py_avataaars/templates/face/eyebrow/flat_natural.svg
py_avataaars/templates/face/eyebrow/frown_natural.svg
py_avataaars/templates/face/eyebrow/raised_excited.svg
py_avataaars/templates/face/eyebrow/raised_excited_natural.svg
py_avataaars/templates/face/eyebrow/sad_concerned.svg
py_avataaars/templates/face/eyebrow/sad_concerned_natural.svg
py_avataaars/templates/face/eyebrow/uni_brow_natural.svg
py_avataaars/templates/face/eyebrow/up_down.svg
py_avataaars/templates/face/eyebrow/up_down_natural.svg
py_avataaars/templates/face/eyes/close.svg
py_avataaars/templates/face/eyes/cry.svg
py_avataaars-1.1.2.dist-info/LICENSE
py_avataaars-1.1.2.dist-info/METADATA
py_avataaars-1.1.2.dist-info/WHEEL
py_avataaars-1.1.2.dist-info/top_level.txt
py_avataaars-1.1.2.dist-info/RECORD
