Metadata-Version: 2.1
Name: py-avataaars
Version: 1.1.2
Summary: Python Avatar generator library
Home-page: https://github.com/kebu/py-avataaars
Author: Krzysztof Ebert
Author-email: krzysztof.ebert@gmail.com
License: MIT
Keywords: Python,Avatar,Avataaars,SVG,PNG,Generator,Library,Graphic,Face,Vector
Platform: UNKNOWN
Classifier: Development Status :: 5 - Production/Stable
Classifier: Intended Audience :: Developers
Classifier: License :: OSI Approved :: MIT License
Classifier: Programming Language :: Python :: Implementation
Classifier: Programming Language :: Python
Classifier: Programming Language :: Python :: 3
Classifier: Programming Language :: Python :: 3.6
Classifier: Programming Language :: Python :: 3.7
Classifier: Programming Language :: Python :: 3.8
Classifier: Topic :: Multimedia :: Graphics
Classifier: Topic :: Multimedia :: Graphics :: Graphics Conversion
Classifier: Topic :: Multimedia :: Graphics :: Presentation
Classifier: Topic :: Software Development :: Libraries
Classifier: Topic :: Software Development :: Libraries :: Python Modules
Classifier: Topic :: Utilities
Requires-Python: >=3.6
